RoboTest/Exp1.py
RoboTest/__init__.py
RoboPack-0.0.2.dist-info/LICENSE
RoboPack-0.0.2.dist-info/METADATA
RoboPack-0.0.2.dist-info/WHEEL
RoboPack-0.0.2.dist-info/top_level.txt
RoboPack-0.0.2.dist-info/RECORD
