Metadata-Version: 2.1
Name: RoboPack
Version: 0.0.2
Summary: Rit
Home-page: UNKNOWN
Author: Ritika
Author-email: ritika.kumar90@gmail.com
License: UNKNOWN
Keywords: arithmetic,robo,mathematics,python tutorial,Ritika kumar
Platform: UNKNOWN
Classifier: Development Status :: 1 - Planning
Classifier: Intended Audience :: Developers
Classifier: Programming Language :: Python :: 3
Classifier: Operating System :: Unix
Classifier: Operating System :: MacOS :: MacOS X
Classifier: Operating System :: Microsoft :: Windows
License-File: LICENSE
